merge_openapi/__init__.py
merge_openapi/__main__.py
merge_openapi-0.1.0.dist-info/entry_points.txt
merge_openapi-0.1.0.dist-info/WHEEL
merge_openapi-0.1.0.dist-info/METADATA
merge_openapi-0.1.0.dist-info/license_files/LICENSE
merge_openapi-0.1.0.dist-info/RECORD
