Metadata-Version: 2.1
Name: merge-openapi
Version: 0.1.0
Summary: Merge all API documentation into a single document!
License: MIT
Author-email: aprilahijriyan <hijriyan23@gmail.com>
Requires-Python: >=3.8
Requires-Dist: requests>=2.28.1
